[
    {
        "title": "Prelude #1",
        "description": "for solo piano",
        "performers": ["Tamami Honma"],
        "track": "./audio/tracks/Prelude.mp3",
        "spotifyLink": "",
        "itunesLink": "",
        "amazonLink": "",
        "deezerLink": "",
        "youtubeLink": ""
    },
    {
        "title": "Felonies",
        "description": "for Soprano and Piano",
        "lyrics": "Felonies",
        "poet": "Jennifer Michael Hecht",
        "poetlink": "http://www.jennifermichaelhecht.com",
        "performers": ["Tamara Hardesty", "Derin &Ouml;ge"],
        "track": "./audio/tracks/Felonies.mp3",
        "spotifyLink": "",
        "itunesLink": "",
        "amazonLink": "",
        "deezerLink": "",
        "youtubeLink": ""
    },
    {
        "title": "Le Petit Basque",
        "description": "for solo piano",
        "performers": ["Tamami Honma"],
        "track": "./audio/tracks/Le Petit Basque.mp3",
        "spotifyLink": "",
        "itunesLink": "",
        "amazonLink": "",
        "deezerLink": "",
        "youtubeLink": ""
    },
    {
        "title": "The Disarrange",
        "description": "for Soprano, Cello, and Piano",
        "lyrics": "TheDisarrange",
        "poet": "Jennifer Michael Hecht",
        "poetlink": "http://www.jennifermichaelhecht.com",
        "performers": ["Tamara Hardesty", "Derin &Ouml;ge", "Jennifer DeVore"],
        "track": "./audio/tracks/The Disarrange.mp3",
        "spotifyLink": "",
        "itunesLink": "",
        "amazonLink": "",
        "deezerLink": "",
        "youtubeLink": ""
    },
    {
        "title": "One",
        "description": "for solo piano",
        "performers": ["Tamami Honma"],
        "track": "./audio/tracks/One.mp3",
        "spotifyLink": "",
        "itunesLink": "",
        "amazonLink": "",
        "deezerLink": "",
        "youtubeLink": ""
    },
    {
        "title": "On the Strength of All Conviction and the Stamina of Love",
        "description": "for Soprano and Piano",
        "lyrics": "OnTheStrength",
        "poet": "Jennifer Michael Hecht",
        "poetlink": "http://www.jennifermichaelhecht.com",
        "performers": ["Tamara Hardesty", "Derin &Ouml;ge"],
        "track": "./audio/tracks/On the strength of all conviction.mp3",
        "spotifyLink": "",
        "itunesLink": "",
        "amazonLink": "",
        "deezerLink": "",
        "youtubeLink": ""
    },
    {
        "title": "This Is Just To Say",
        "description": "for Soprano and Piano",
        "lyrics": "ThisIsJustToSay",
        "poet": "William Carlos Williams",
        "performers": ["Tamara Hardesty", "Derin &Ouml;ge"],
        "track": "./audio/tracks/This is just to say.mp3",
        "spotifyLink": "",
        "itunesLink": "",
        "amazonLink": "",
        "deezerLink": "",
        "youtubeLink": ""
    },
    {
        "title": "Demeter",
        "description": "for solo piano",
        "performers": ["Tamami Honma"],
        "track": "./audio/tracks/Demeter.mp3",
        "spotifyLink": "",
        "itunesLink": "",
        "amazonLink": "",
        "deezerLink": "",
        "youtubeLink": ""
    },
    {
        "title": "Time Does Not Bring Relief<span class='note'>*</span>",
        "description": "for Soprano and Piano Quintet",
        "lyrics": "TimeDoesNotBringRelief",
        "poet": "Edna St. Vincent Millay",
        "performers": ["Heather Green", "Gene Pritsker", "Amir Khosrowpour", "Lynn Bechtold", "Mioi Takeda", "Jennifer DeVore"],
        "track": "./audio/tracks/Time Does Not Bring Relief.mp3",
        "spotifyLink": "",
        "itunesLink": "",
        "amazonLink": "",
        "deezerLink": "",
        "youtubeLink": ""
    },
    {
        "title": "Worms<span class='note'>*</span>",
        "description": "for Soprano and Piano Quintet",
        "lyrics": "Worms",
        "poet": "Heather Green",
        "performers": ["Heather Green", "Gene Pritsker", "Amir Khosrowpour", "Lynn Bechtold", "Mioi Takeda", "Jennifer DeVore"],
        "track": "./audio/tracks/Worms.mp3",
        "spotifyLink": "",
        "itunesLink": "",
        "amazonLink": "",
        "deezerLink": "",
        "youtubeLink": ""
    },
    {
        "title": "Slow Motion",
        "description": "for solo piano",
        "performers": ["Tamami Honma"],
        "track": "./audio/tracks/Slow motion.mp3",
        "spotifyLink": "",
        "itunesLink": "",
        "amazonLink": "",
        "deezerLink": "",
        "youtubeLink": ""
    },
    {
        "title": "Dark Hills",
        "description": "for Soprano and Piano",
        "lyrics": "TheDarkHills",
        "poet": "Edwin Arlington Robinson",
        "performers": ["Tamara Hardesty", "Derin &Ouml;ge"],
        "track": "./audio/tracks/Dark Hills.mp3",
        "spotifyLink": "",
        "itunesLink": "",
        "amazonLink": "",
        "deezerLink": "",
        "youtubeLink": ""
    },
    {
        "title": "After a Hundred Years",
        "description": "for Soprano and Piano",
        "lyrics": "AfterAHundredYears",
        "poet": "Emily Dickinson",
        "performers": ["Tamara Hardesty", "Derin &Ouml;ge"],
        "track": "./audio/tracks/After a Hundred Years.mp3",
        "spotifyLink": "",
        "itunesLink": "",
        "amazonLink": "",
        "deezerLink": "",
        "youtubeLink": ""
    },
    {
        "title": "I Thought My Heart Had Forgotten",
        "description": "for Soprano and Piano",
        "lyrics": "IThoughtMyHeartHadForgotten",
        "poet": "Alexander Pushkin",
        "performers": ["Tamara Hardesty", "Derin &Ouml;ge"],
        "track": "./audio/tracks/I thought my heart had forgotten.mp3",
        "spotifyLink": "",
        "itunesLink": "",
        "amazonLink": "",
        "deezerLink": "",
        "youtubeLink": ""
    },
    {
        "title": "Musing",
        "description": "for piano solo",
        "performers": ["Tamami Honma"],
        "track": "./audio/tracks/Musing.mp3",
        "spotifyLink": "",
        "itunesLink": "",
        "amazonLink": "",
        "deezerLink": "",
        "youtubeLink": ""
    }
]
